simulator_tgq/QuantumCircuit.py
simulator_tgq/__init__.py
simulator_tgq/draw_circuit_tools.py
QuantumCircuit-0.4.0.dist-info/LICENSE
QuantumCircuit-0.4.0.dist-info/METADATA
QuantumCircuit-0.4.0.dist-info/WHEEL
QuantumCircuit-0.4.0.dist-info/top_level.txt
QuantumCircuit-0.4.0.dist-info/RECORD
