Metadata-Version: 2.1
Name: QuantumCircuit
Version: 0.4.0
Summary: CETC量子模拟器
Home-page: UNKNOWN
Author: CETC
Author-email: wangzhiqiang@tgqs.net
License: MIT
Platform: UNKNOWN
Classifier: Operating System :: OS Independent
Classifier: License :: OSI Approved :: MIT License
Classifier: Programming Language :: Python :: 3
License-File: LICENSE
Requires-Dist: numpy (==1.24.3)
Requires-Dist: numba (==0.58.1)
Requires-Dist: matplotlib (==3.7.1)
